{
  "schema_version": "1.2",
  "ticker": "SMH",
  "stamp": {
    "timestamp_fetch": "2026-07-21T21:31:20+02:00",
    "data_type": "delayed",
    "lag_stimato_min": 20,
    "usage_layer": "context",
    "lake_status": "ready"
  },
  "underlying": {
    "symbol": "SMH",
    "conId": 229725622,
    "exchange": "NASDAQ",
    "currency": "USD",
    "spot": 582.48,
    "open": 581.49,
    "high": 585.66,
    "low": 572.05,
    "prior_close": 558.83,
    "volume": 143637.0,
    "change_pct": 4.23,
    "iv_underlying": 0.571,
    "hv": 0.634,
    "iv_rank_52w": 86.1,
    "iv_percentile_52w": 96.4,
    "week52_high": 671.83,
    "week52_low": 279.19,
    "avg_volume_20d": 9253428,
    "vwap": 581.152,
    "vwap_source": "yahoo",
    "vwap_method": "VWAP typical-price barre 1m SMH sessione corrente",
    "poc": 583.036,
    "poc_source": "yahoo",
    "poc_method": "volume-profile 50 bin, barre 5m SMH sessione corrente",
    "oi_totals": {
      "call": 575127.0,
      "put": 1653685.0,
      "put_call": 2.875
    }
  },
  "data_availability": {
    "hv": "ok",
    "iv_rank_52w": "ok",
    "iv_percentile_52w": "ok",
    "avg_volume_20d": "ok",
    "week52_high": "ok",
    "week52_low": "ok",
    "vwap": "ok",
    "poc": "ok",
    "ohlcv": "ok"
  },
  "option_params": {
    "exchange": "EMERALD",
    "trading_class": "SMH",
    "multiplier": "100",
    "currency": "USD",
    "source": "reqSecDefOptParams"
  },
  "expirations": [
    "20260722",
    "20260724"
  ],
  "bs_assumptions": {
    "r": 0.04,
    "q": 0.002,
    "q_source": "dividendo_annuo/spot (tick 456)",
    "daycount": "ACT/365",
    "price_used": "mid"
  },
  "options": [
    {
      "expiry": "20260722",
      "strike": 562.5,
      "right": "C",
      "bid": null,
      "ask": null,
      "mid": 19.986,
      "last": null,
      "iv": 0.607,
      "iv_model": null,
      "iv_bs": null,
      "iv_reliable": true,
      "delta": 1.0,
      "gamma": 0.0,
      "vega": 0.0,
      "theta": -0.091,
      "open_interest": null,
      "volume": null,
      "discrepancy": false,
      "discrepancy_detail": null,
      "source": "bs-interp"
    },
    {
      "expiry": "20260722",
      "strike": 562.5,
      "right": "P",
      "bid": 1.44,
      "ask": 2.06,
      "mid": 1.75,
      "last": 1.56,
      "iv": null,
      "iv_model": null,
      "iv_bs": null,
      "iv_reliable": false,
      "delta": -0.159,
      "delta_bs": -0.159,
      "gamma": 0.012,
      "vega": 0.024,
      "theta": -24.224,
      "open_interest": 45.0,
      "volume": 27.0,
      "discrepancy": false,
      "discrepancy_detail": null,
      "source": "tws"
    },
    {
      "expiry": "20260722",
      "strike": 565.0,
      "right": "C",
      "bid": null,
      "ask": null,
      "mid": 17.488,
      "last": null,
      "iv": 0.607,
      "iv_model": null,
      "iv_bs": null,
      "iv_reliable": true,
      "delta": 0.999,
      "gamma": 0.001,
      "vega": 0.0,
      "theta": -0.19,
      "open_interest": null,
      "volume": null,
      "discrepancy": false,
      "discrepancy_detail": null,
      "source": "bs-interp"
    },
    {
      "expiry": "20260722",
      "strike": 565.0,
      "right": "P",
      "bid": null,
      "ask": null,
      "mid": 0.002,
      "last": null,
      "iv": 0.607,
      "iv_model": null,
      "iv_bs": null,
      "iv_reliable": true,
      "delta": -0.001,
      "gamma": 0.001,
      "vega": 0.0,
      "theta": -0.131,
      "open_interest": null,
      "volume": null,
      "discrepancy": false,
      "discrepancy_detail": null,
      "source": "bs-interp"
    },
    {
      "expiry": "20260722",
      "strike": 567.5,
      "right": "C",
      "bid": null,
      "ask": null,
      "mid": 14.996,
      "last": null,
      "iv": 0.607,
      "iv_model": null,
      "iv_bs": null,
      "iv_reliable": true,
      "delta": 0.995,
      "gamma": 0.003,
      "vega": 0.002,
      "theta": -0.493,
      "open_interest": null,
      "volume": null,
      "discrepancy": false,
      "discrepancy_detail": null,
      "source": "bs-interp"
    },
    {
      "expiry": "20260722",
      "strike": 567.5,
      "right": "P",
      "bid": 2.05,
      "ask": 3.0,
      "mid": 2.525,
      "last": 2.33,
      "iv": null,
      "iv_model": null,
      "iv_bs": null,
      "iv_reliable": false,
      "delta": -0.218,
      "delta_bs": -0.218,
      "gamma": 0.015,
      "vega": 0.029,
      "theta": -28.395,
      "open_interest": 18.0,
      "volume": 109.0,
      "discrepancy": false,
      "discrepancy_detail": null,
      "source": "tws"
    },
    {
      "expiry": "20260722",
      "strike": 570.0,
      "right": "C",
      "bid": null,
      "ask": null,
      "mid": 12.522,
      "last": null,
      "iv": 0.607,
      "iv_model": null,
      "iv_bs": null,
      "iv_reliable": true,
      "delta": 0.983,
      "gamma": 0.007,
      "vega": 0.004,
      "theta": -1.251,
      "open_interest": null,
      "volume": null,
      "discrepancy": false,
      "discrepancy_detail": null,
      "source": "bs-interp"
    },
    {
      "expiry": "20260722",
      "strike": 570.0,
      "right": "P",
      "bid": null,
      "ask": null,
      "mid": 0.036,
      "last": null,
      "iv": 0.607,
      "iv_model": null,
      "iv_bs": null,
      "iv_reliable": true,
      "delta": -0.017,
      "gamma": 0.007,
      "vega": 0.004,
      "theta": -1.191,
      "open_interest": null,
      "volume": null,
      "discrepancy": false,
      "discrepancy_detail": null,
      "source": "bs-interp"
    },
    {
      "expiry": "20260722",
      "strike": 572.5,
      "right": "C",
      "bid": null,
      "ask": null,
      "mid": 10.095,
      "last": null,
      "iv": 0.607,
      "iv_model": null,
      "iv_bs": null,
      "iv_reliable": true,
      "delta": 0.955,
      "gamma": 0.016,
      "vega": 0.009,
      "theta": -2.767,
      "open_interest": null,
      "volume": null,
      "discrepancy": false,
      "discrepancy_detail": null,
      "source": "bs-interp"
    },
    {
      "expiry": "20260722",
      "strike": 572.5,
      "right": "P",
      "bid": 3.35,
      "ask": 4.0,
      "mid": 3.675,
      "last": 3.5,
      "iv": null,
      "iv_model": null,
      "iv_bs": null,
      "iv_reliable": false,
      "delta": -0.296,
      "delta_bs": -0.296,
      "gamma": 0.018,
      "vega": 0.034,
      "theta": -32.352,
      "open_interest": 165.0,
      "volume": 103.0,
      "discrepancy": false,
      "discrepancy_detail": null,
      "source": "tws"
    },
    {
      "expiry": "20260722",
      "strike": 575.0,
      "right": "C",
      "bid": null,
      "ask": null,
      "mid": 7.774,
      "last": null,
      "iv": 0.607,
      "iv_model": null,
      "iv_bs": null,
      "iv_reliable": true,
      "delta": 0.898,
      "gamma": 0.03,
      "vega": 0.017,
      "theta": -5.164,
      "open_interest": null,
      "volume": null,
      "discrepancy": false,
      "discrepancy_detail": null,
      "source": "bs-interp"
    },
    {
      "expiry": "20260722",
      "strike": 575.0,
      "right": "P",
      "bid": null,
      "ask": null,
      "mid": 0.288,
      "last": null,
      "iv": 0.607,
      "iv_model": null,
      "iv_bs": null,
      "iv_reliable": true,
      "delta": -0.102,
      "gamma": 0.03,
      "vega": 0.017,
      "theta": -5.104,
      "open_interest": null,
      "volume": null,
      "discrepancy": false,
      "discrepancy_detail": null,
      "source": "bs-interp"
    },
    {
      "expiry": "20260722",
      "strike": 577.5,
      "right": "C",
      "bid": null,
      "ask": null,
      "mid": 5.646,
      "last": null,
      "iv": 0.607,
      "iv_model": null,
      "iv_bs": null,
      "iv_reliable": true,
      "delta": 0.802,
      "gamma": 0.047,
      "vega": 0.027,
      "theta": -8.068,
      "open_interest": null,
      "volume": null,
      "discrepancy": false,
      "discrepancy_detail": null,
      "source": "bs-interp"
    },
    {
      "expiry": "20260722",
      "strike": 577.5,
      "right": "P",
      "bid": 4.5,
      "ask": 5.6,
      "mid": 5.05,
      "last": 4.45,
      "iv": null,
      "iv_model": null,
      "iv_bs": null,
      "iv_reliable": false,
      "delta": -0.386,
      "delta_bs": -0.386,
      "gamma": 0.021,
      "vega": 0.037,
      "theta": -33.903,
      "open_interest": 11.0,
      "volume": 43.0,
      "discrepancy": false,
      "discrepancy_detail": null,
      "source": "tws"
    },
    {
      "expiry": "20260722",
      "strike": 580.0,
      "right": "C",
      "bid": null,
      "ask": null,
      "mid": 3.814,
      "last": null,
      "iv": 0.607,
      "iv_model": null,
      "iv_bs": null,
      "iv_reliable": true,
      "delta": 0.664,
      "gamma": 0.061,
      "vega": 0.036,
      "theta": -10.537,
      "open_interest": null,
      "volume": null,
      "discrepancy": false,
      "discrepancy_detail": null,
      "source": "bs-interp"
    },
    {
      "expiry": "20260722",
      "strike": 580.0,
      "right": "P",
      "bid": null,
      "ask": null,
      "mid": 1.328,
      "last": null,
      "iv": 0.607,
      "iv_model": null,
      "iv_bs": null,
      "iv_reliable": true,
      "delta": -0.336,
      "gamma": 0.061,
      "vega": 0.036,
      "theta": -10.476,
      "open_interest": null,
      "volume": null,
      "discrepancy": false,
      "discrepancy_detail": null,
      "source": "bs-interp"
    },
    {
      "expiry": "20260722",
      "strike": 582.5,
      "right": "C",
      "bid": 6.75,
      "ask": 7.85,
      "mid": 7.3,
      "last": 8.1,
      "iv": 0.607,
      "iv_model": 0.607,
      "iv_bs": null,
      "iv_reliable": true,
      "delta": 0.506,
      "delta_bs": 0.501,
      "gamma": 0.067,
      "vega": 0.039,
      "theta": -11.515,
      "open_interest": 15.0,
      "volume": 150.0,
      "discrepancy": false,
      "discrepancy_detail": null,
      "source": "tws"
    },
    {
      "expiry": "20260722",
      "strike": 582.5,
      "right": "P",
      "bid": null,
      "ask": null,
      "mid": 2.378,
      "last": null,
      "iv": 0.607,
      "iv_model": null,
      "iv_bs": null,
      "iv_reliable": true,
      "delta": -0.499,
      "gamma": 0.067,
      "vega": 0.039,
      "theta": -11.455,
      "open_interest": null,
      "volume": null,
      "discrepancy": false,
      "discrepancy_detail": null,
      "source": "bs-interp"
    },
    {
      "expiry": "20260722",
      "strike": 585.0,
      "right": "C",
      "bid": null,
      "ask": null,
      "mid": 1.328,
      "last": null,
      "iv": 0.607,
      "iv_model": null,
      "iv_bs": null,
      "iv_reliable": true,
      "delta": 0.338,
      "gamma": 0.062,
      "vega": 0.036,
      "theta": -10.55,
      "open_interest": null,
      "volume": null,
      "discrepancy": false,
      "discrepancy_detail": null,
      "source": "bs-interp"
    },
    {
      "expiry": "20260722",
      "strike": 585.0,
      "right": "P",
      "bid": null,
      "ask": null,
      "mid": 3.842,
      "last": null,
      "iv": 0.607,
      "iv_model": null,
      "iv_bs": null,
      "iv_reliable": true,
      "delta": -0.662,
      "gamma": 0.062,
      "vega": 0.036,
      "theta": -10.489,
      "open_interest": null,
      "volume": null,
      "discrepancy": false,
      "discrepancy_detail": null,
      "source": "bs-interp"
    },
    {
      "expiry": "20260722",
      "strike": 587.5,
      "right": "C",
      "bid": 4.45,
      "ask": 5.2,
      "mid": 4.825,
      "last": 5.5,
      "iv": null,
      "iv_model": null,
      "iv_bs": null,
      "iv_reliable": false,
      "delta": 0.394,
      "delta_bs": 0.394,
      "gamma": 0.022,
      "vega": 0.038,
      "theta": -32.818,
      "open_interest": 103.0,
      "volume": 345.0,
      "discrepancy": false,
      "discrepancy_detail": null,
      "source": "tws"
    },
    {
      "expiry": "20260722",
      "strike": 587.5,
      "right": "P",
      "bid": null,
      "ask": null,
      "mid": 5.682,
      "last": null,
      "iv": 0.607,
      "iv_model": null,
      "iv_bs": null,
      "iv_reliable": true,
      "delta": -0.798,
      "gamma": 0.047,
      "vega": 0.028,
      "theta": -8.058,
      "open_interest": null,
      "volume": null,
      "discrepancy": false,
      "discrepancy_detail": null,
      "source": "bs-interp"
    },
    {
      "expiry": "20260722",
      "strike": 590.0,
      "right": "C",
      "bid": null,
      "ask": null,
      "mid": 0.299,
      "last": null,
      "iv": 0.607,
      "iv_model": null,
      "iv_bs": null,
      "iv_reliable": true,
      "delta": 0.105,
      "gamma": 0.031,
      "vega": 0.018,
      "theta": -5.26,
      "open_interest": null,
      "volume": null,
      "discrepancy": false,
      "discrepancy_detail": null,
      "source": "bs-interp"
    },
    {
      "expiry": "20260722",
      "strike": 590.0,
      "right": "P",
      "bid": null,
      "ask": null,
      "mid": 7.813,
      "last": null,
      "iv": 0.607,
      "iv_model": null,
      "iv_bs": null,
      "iv_reliable": true,
      "delta": -0.894,
      "gamma": 0.031,
      "vega": 0.018,
      "theta": -5.198,
      "open_interest": null,
      "volume": null,
      "discrepancy": false,
      "discrepancy_detail": null,
      "source": "bs-interp"
    },
    {
      "expiry": "20260722",
      "strike": 592.5,
      "right": "C",
      "bid": 2.85,
      "ask": 3.5,
      "mid": 3.175,
      "last": 3.06,
      "iv": null,
      "iv_model": null,
      "iv_bs": null,
      "iv_reliable": false,
      "delta": 0.292,
      "delta_bs": 0.292,
      "gamma": 0.019,
      "vega": 0.034,
      "theta": -29.282,
      "open_interest": 104.0,
      "volume": 149.0,
      "discrepancy": false,
      "discrepancy_detail": null,
      "source": "tws"
    },
    {
      "expiry": "20260722",
      "strike": 592.5,
      "right": "P",
      "bid": null,
      "ask": null,
      "mid": 10.132,
      "last": null,
      "iv": 0.607,
      "iv_model": null,
      "iv_bs": null,
      "iv_reliable": true,
      "delta": -0.952,
      "gamma": 0.017,
      "vega": 0.01,
      "theta": -2.812,
      "open_interest": null,
      "volume": null,
      "discrepancy": false,
      "discrepancy_detail": null,
      "source": "bs-interp"
    },
    {
      "expiry": "20260722",
      "strike": 595.0,
      "right": "C",
      "bid": null,
      "ask": null,
      "mid": 0.041,
      "last": null,
      "iv": 0.607,
      "iv_model": null,
      "iv_bs": null,
      "iv_reliable": true,
      "delta": 0.019,
      "gamma": 0.008,
      "vega": 0.004,
      "theta": -1.328,
      "open_interest": null,
      "volume": null,
      "discrepancy": false,
      "discrepancy_detail": null,
      "source": "bs-interp"
    },
    {
      "expiry": "20260722",
      "strike": 595.0,
      "right": "P",
      "bid": null,
      "ask": null,
      "mid": 12.554,
      "last": null,
      "iv": 0.607,
      "iv_model": null,
      "iv_bs": null,
      "iv_reliable": true,
      "delta": -0.981,
      "gamma": 0.008,
      "vega": 0.004,
      "theta": -1.266,
      "open_interest": null,
      "volume": null,
      "discrepancy": false,
      "discrepancy_detail": null,
      "source": "bs-interp"
    },
    {
      "expiry": "20260722",
      "strike": 597.5,
      "right": "C",
      "bid": 1.69,
      "ask": 2.44,
      "mid": 2.065,
      "last": 2.23,
      "iv": null,
      "iv_model": null,
      "iv_bs": null,
      "iv_reliable": false,
      "delta": 0.208,
      "delta_bs": 0.208,
      "gamma": 0.016,
      "vega": 0.028,
      "theta": -24.802,
      "open_interest": 36.0,
      "volume": 116.0,
      "discrepancy": false,
      "discrepancy_detail": null,
      "source": "tws"
    },
    {
      "expiry": "20260722",
      "strike": 597.5,
      "right": "P",
      "bid": null,
      "ask": null,
      "mid": 15.026,
      "last": null,
      "iv": 0.607,
      "iv_model": null,
      "iv_bs": null,
      "iv_reliable": true,
      "delta": -0.994,
      "gamma": 0.003,
      "vega": 0.002,
      "theta": -0.457,
      "open_interest": null,
      "volume": null,
      "discrepancy": false,
      "discrepancy_detail": null,
      "source": "bs-interp"
    },
    {
      "expiry": "20260722",
      "strike": 600.0,
      "right": "C",
      "bid": null,
      "ask": null,
      "mid": 0.003,
      "last": null,
      "iv": 0.607,
      "iv_model": null,
      "iv_bs": null,
      "iv_reliable": true,
      "delta": 0.002,
      "gamma": 0.001,
      "vega": 0.001,
      "theta": -0.173,
      "open_interest": null,
      "volume": null,
      "discrepancy": false,
      "discrepancy_detail": null,
      "source": "bs-interp"
    },
    {
      "expiry": "20260722",
      "strike": 600.0,
      "right": "P",
      "bid": null,
      "ask": null,
      "mid": 17.517,
      "last": null,
      "iv": 0.607,
      "iv_model": null,
      "iv_bs": null,
      "iv_reliable": true,
      "delta": -0.998,
      "gamma": 0.001,
      "vega": 0.001,
      "theta": -0.11,
      "open_interest": null,
      "volume": null,
      "discrepancy": false,
      "discrepancy_detail": null,
      "source": "bs-interp"
    },
    {
      "expiry": "20260722",
      "strike": 602.5,
      "right": "C",
      "bid": 1.02,
      "ask": 1.6,
      "mid": 1.31,
      "last": 1.65,
      "iv": null,
      "iv_model": null,
      "iv_bs": null,
      "iv_reliable": false,
      "delta": 0.143,
      "delta_bs": 0.143,
      "gamma": 0.012,
      "vega": 0.022,
      "theta": -19.856,
      "open_interest": 56.0,
      "volume": 46.0,
      "discrepancy": false,
      "discrepancy_detail": null,
      "source": "tws"
    },
    {
      "expiry": "20260722",
      "strike": 602.5,
      "right": "P",
      "bid": null,
      "ask": null,
      "mid": 20.014,
      "last": null,
      "iv": 0.607,
      "iv_model": null,
      "iv_bs": null,
      "iv_reliable": true,
      "delta": -1.0,
      "gamma": 0.0,
      "vega": 0.0,
      "theta": 0.014,
      "open_interest": null,
      "volume": null,
      "discrepancy": false,
      "discrepancy_detail": null,
      "source": "bs-interp"
    },
    {
      "expiry": "20260724",
      "strike": 562.5,
      "right": "C",
      "bid": null,
      "ask": null,
      "mid": 26.428,
      "last": null,
      "iv": 0.817,
      "iv_model": null,
      "iv_bs": null,
      "iv_reliable": true,
      "delta": 0.725,
      "gamma": 0.009,
      "vega": 0.148,
      "theta": -2.909,
      "open_interest": null,
      "volume": null,
      "discrepancy": false,
      "discrepancy_detail": null,
      "source": "bs-interp"
    },
    {
      "expiry": "20260724",
      "strike": 562.5,
      "right": "P",
      "bid": 6.05,
      "ask": 6.6,
      "mid": 6.325,
      "last": 5.85,
      "iv": 0.817,
      "iv_model": null,
      "iv_bs": 0.817,
      "iv_reliable": true,
      "delta": -0.275,
      "delta_bs": -0.275,
      "gamma": 0.009,
      "vega": 0.148,
      "theta": -2.85,
      "open_interest": 708.0,
      "volume": 87.0,
      "discrepancy": false,
      "discrepancy_detail": null,
      "source": "tws"
    },
    {
      "expiry": "20260724",
      "strike": 565.0,
      "right": "C",
      "bid": null,
      "ask": null,
      "mid": 24.613,
      "last": null,
      "iv": 0.812,
      "iv_model": null,
      "iv_bs": null,
      "iv_reliable": true,
      "delta": 0.702,
      "gamma": 0.01,
      "vega": 0.153,
      "theta": -2.999,
      "open_interest": null,
      "volume": null,
      "discrepancy": false,
      "discrepancy_detail": null,
      "source": "bs-interp"
    },
    {
      "expiry": "20260724",
      "strike": 565.0,
      "right": "P",
      "bid": null,
      "ask": null,
      "mid": 7.009,
      "last": null,
      "iv": 0.812,
      "iv_model": null,
      "iv_bs": null,
      "iv_reliable": true,
      "delta": -0.298,
      "gamma": 0.01,
      "vega": 0.153,
      "theta": -2.94,
      "open_interest": null,
      "volume": null,
      "discrepancy": false,
      "discrepancy_detail": null,
      "source": "bs-interp"
    },
    {
      "expiry": "20260724",
      "strike": 567.5,
      "right": "C",
      "bid": null,
      "ask": null,
      "mid": 22.854,
      "last": null,
      "iv": 0.806,
      "iv_model": null,
      "iv_bs": null,
      "iv_reliable": true,
      "delta": 0.677,
      "gamma": 0.01,
      "vega": 0.159,
      "theta": -3.079,
      "open_interest": null,
      "volume": null,
      "discrepancy": false,
      "discrepancy_detail": null,
      "source": "bs-interp"
    },
    {
      "expiry": "20260724",
      "strike": 567.5,
      "right": "P",
      "bid": 7.4,
      "ask": 8.1,
      "mid": 7.75,
      "last": 7.6,
      "iv": 0.806,
      "iv_model": null,
      "iv_bs": 0.806,
      "iv_reliable": true,
      "delta": -0.323,
      "delta_bs": -0.323,
      "gamma": 0.01,
      "vega": 0.159,
      "theta": -3.019,
      "open_interest": 477.0,
      "volume": 183.0,
      "discrepancy": false,
      "discrepancy_detail": null,
      "source": "tws"
    },
    {
      "expiry": "20260724",
      "strike": 570.0,
      "right": "C",
      "bid": null,
      "ask": null,
      "mid": 21.124,
      "last": null,
      "iv": 0.798,
      "iv_model": null,
      "iv_bs": null,
      "iv_reliable": true,
      "delta": 0.652,
      "gamma": 0.01,
      "vega": 0.163,
      "theta": -3.137,
      "open_interest": null,
      "volume": null,
      "discrepancy": false,
      "discrepancy_detail": null,
      "source": "bs-interp"
    },
    {
      "expiry": "20260724",
      "strike": 570.0,
      "right": "P",
      "bid": null,
      "ask": null,
      "mid": 8.519,
      "last": null,
      "iv": 0.798,
      "iv_model": null,
      "iv_bs": null,
      "iv_reliable": true,
      "delta": -0.348,
      "gamma": 0.01,
      "vega": 0.163,
      "theta": -3.078,
      "open_interest": null,
      "volume": null,
      "discrepancy": false,
      "discrepancy_detail": null,
      "source": "bs-interp"
    },
    {
      "expiry": "20260724",
      "strike": 572.5,
      "right": "C",
      "bid": null,
      "ask": null,
      "mid": 19.456,
      "last": null,
      "iv": 0.79,
      "iv_model": null,
      "iv_bs": null,
      "iv_reliable": true,
      "delta": 0.626,
      "gamma": 0.011,
      "vega": 0.168,
      "theta": -3.183,
      "open_interest": null,
      "volume": null,
      "discrepancy": false,
      "discrepancy_detail": null,
      "source": "bs-interp"
    },
    {
      "expiry": "20260724",
      "strike": 572.5,
      "right": "P",
      "bid": 9.0,
      "ask": 9.7,
      "mid": 9.35,
      "last": 8.6,
      "iv": 0.79,
      "iv_model": null,
      "iv_bs": 0.79,
      "iv_reliable": true,
      "delta": -0.374,
      "delta_bs": -0.374,
      "gamma": 0.011,
      "vega": 0.168,
      "theta": -3.124,
      "open_interest": 105.0,
      "volume": 36.0,
      "discrepancy": false,
      "discrepancy_detail": null,
      "source": "tws"
    },
    {
      "expiry": "20260724",
      "strike": 575.0,
      "right": "C",
      "bid": null,
      "ask": null,
      "mid": 17.885,
      "last": null,
      "iv": 0.785,
      "iv_model": null,
      "iv_bs": null,
      "iv_reliable": true,
      "delta": 0.599,
      "gamma": 0.011,
      "vega": 0.171,
      "theta": -3.223,
      "open_interest": null,
      "volume": null,
      "discrepancy": false,
      "discrepancy_detail": null,
      "source": "bs-interp"
    },
    {
      "expiry": "20260724",
      "strike": 575.0,
      "right": "P",
      "bid": null,
      "ask": null,
      "mid": 10.279,
      "last": null,
      "iv": 0.785,
      "iv_model": null,
      "iv_bs": null,
      "iv_reliable": true,
      "delta": -0.401,
      "gamma": 0.011,
      "vega": 0.171,
      "theta": -3.163,
      "open_interest": null,
      "volume": null,
      "discrepancy": false,
      "discrepancy_detail": null,
      "source": "bs-interp"
    },
    {
      "expiry": "20260724",
      "strike": 577.5,
      "right": "C",
      "bid": null,
      "ask": null,
      "mid": 16.382,
      "last": null,
      "iv": 0.779,
      "iv_model": null,
      "iv_bs": null,
      "iv_reliable": true,
      "delta": 0.571,
      "gamma": 0.011,
      "vega": 0.174,
      "theta": -3.248,
      "open_interest": null,
      "volume": null,
      "discrepancy": false,
      "discrepancy_detail": null,
      "source": "bs-interp"
    },
    {
      "expiry": "20260724",
      "strike": 577.5,
      "right": "P",
      "bid": 10.9,
      "ask": 11.65,
      "mid": 11.275,
      "last": 11.35,
      "iv": 0.779,
      "iv_model": null,
      "iv_bs": 0.779,
      "iv_reliable": true,
      "delta": -0.429,
      "delta_bs": -0.429,
      "gamma": 0.011,
      "vega": 0.174,
      "theta": -3.187,
      "open_interest": 47.0,
      "volume": 43.0,
      "discrepancy": false,
      "discrepancy_detail": null,
      "source": "tws"
    },
    {
      "expiry": "20260724",
      "strike": 580.0,
      "right": "C",
      "bid": null,
      "ask": null,
      "mid": 14.893,
      "last": null,
      "iv": 0.77,
      "iv_model": null,
      "iv_bs": null,
      "iv_reliable": true,
      "delta": 0.542,
      "gamma": 0.012,
      "vega": 0.175,
      "theta": -3.242,
      "open_interest": null,
      "volume": null,
      "discrepancy": false,
      "discrepancy_detail": null,
      "source": "bs-interp"
    },
    {
      "expiry": "20260724",
      "strike": 580.0,
      "right": "P",
      "bid": null,
      "ask": null,
      "mid": 12.286,
      "last": null,
      "iv": 0.77,
      "iv_model": null,
      "iv_bs": null,
      "iv_reliable": true,
      "delta": -0.458,
      "gamma": 0.012,
      "vega": 0.175,
      "theta": -3.182,
      "open_interest": null,
      "volume": null,
      "discrepancy": false,
      "discrepancy_detail": null,
      "source": "bs-interp"
    },
    {
      "expiry": "20260724",
      "strike": 582.5,
      "right": "C",
      "bid": 13.15,
      "ask": 13.8,
      "mid": 13.475,
      "last": 14.6,
      "iv": 0.761,
      "iv_model": null,
      "iv_bs": 0.761,
      "iv_reliable": true,
      "delta": 0.513,
      "delta_bs": 0.513,
      "gamma": 0.012,
      "vega": 0.176,
      "theta": -3.219,
      "open_interest": 212.0,
      "volume": 108.0,
      "discrepancy": false,
      "discrepancy_detail": null,
      "source": "tws"
    },
    {
      "expiry": "20260724",
      "strike": 582.5,
      "right": "P",
      "bid": null,
      "ask": null,
      "mid": 13.367,
      "last": null,
      "iv": 0.761,
      "iv_model": null,
      "iv_bs": null,
      "iv_reliable": true,
      "delta": -0.487,
      "gamma": 0.012,
      "vega": 0.176,
      "theta": -3.159,
      "open_interest": null,
      "volume": null,
      "discrepancy": false,
      "discrepancy_detail": null,
      "source": "bs-interp"
    },
    {
      "expiry": "20260724",
      "strike": 585.0,
      "right": "C",
      "bid": null,
      "ask": null,
      "mid": 12.2,
      "last": null,
      "iv": 0.756,
      "iv_model": null,
      "iv_bs": null,
      "iv_reliable": true,
      "delta": 0.483,
      "gamma": 0.012,
      "vega": 0.176,
      "theta": -3.196,
      "open_interest": null,
      "volume": null,
      "discrepancy": false,
      "discrepancy_detail": null,
      "source": "bs-interp"
    },
    {
      "expiry": "20260724",
      "strike": 585.0,
      "right": "P",
      "bid": null,
      "ask": null,
      "mid": 14.592,
      "last": null,
      "iv": 0.756,
      "iv_model": null,
      "iv_bs": null,
      "iv_reliable": true,
      "delta": -0.517,
      "gamma": 0.012,
      "vega": 0.176,
      "theta": -3.135,
      "open_interest": null,
      "volume": null,
      "discrepancy": false,
      "discrepancy_detail": null,
      "source": "bs-interp"
    },
    {
      "expiry": "20260724",
      "strike": 587.5,
      "right": "C",
      "bid": 10.65,
      "ask": 11.35,
      "mid": 11.0,
      "last": 12.0,
      "iv": 0.751,
      "iv_model": null,
      "iv_bs": 0.751,
      "iv_reliable": true,
      "delta": 0.453,
      "delta_bs": 0.453,
      "gamma": 0.012,
      "vega": 0.175,
      "theta": -3.154,
      "open_interest": 186.0,
      "volume": 48.0,
      "discrepancy": false,
      "discrepancy_detail": null,
      "source": "tws"
    },
    {
      "expiry": "20260724",
      "strike": 587.5,
      "right": "P",
      "bid": null,
      "ask": null,
      "mid": 15.891,
      "last": null,
      "iv": 0.751,
      "iv_model": null,
      "iv_bs": null,
      "iv_reliable": true,
      "delta": -0.547,
      "gamma": 0.012,
      "vega": 0.175,
      "theta": -3.093,
      "open_interest": null,
      "volume": null,
      "discrepancy": false,
      "discrepancy_detail": null,
      "source": "bs-interp"
    },
    {
      "expiry": "20260724",
      "strike": 590.0,
      "right": "C",
      "bid": null,
      "ask": null,
      "mid": 9.875,
      "last": null,
      "iv": 0.746,
      "iv_model": null,
      "iv_bs": null,
      "iv_reliable": true,
      "delta": 0.423,
      "gamma": 0.012,
      "vega": 0.173,
      "theta": -3.095,
      "open_interest": null,
      "volume": null,
      "discrepancy": false,
      "discrepancy_detail": null,
      "source": "bs-interp"
    },
    {
      "expiry": "20260724",
      "strike": 590.0,
      "right": "P",
      "bid": null,
      "ask": null,
      "mid": 17.265,
      "last": null,
      "iv": 0.746,
      "iv_model": null,
      "iv_bs": null,
      "iv_reliable": true,
      "delta": -0.577,
      "gamma": 0.012,
      "vega": 0.173,
      "theta": -3.034,
      "open_interest": null,
      "volume": null,
      "discrepancy": false,
      "discrepancy_detail": null,
      "source": "bs-interp"
    },
    {
      "expiry": "20260724",
      "strike": 592.5,
      "right": "C",
      "bid": 8.5,
      "ask": 9.15,
      "mid": 8.825,
      "last": 9.7,
      "iv": 0.741,
      "iv_model": null,
      "iv_bs": 0.741,
      "iv_reliable": true,
      "delta": 0.393,
      "delta_bs": 0.393,
      "gamma": 0.012,
      "vega": 0.17,
      "theta": -3.019,
      "open_interest": 114.0,
      "volume": 105.0,
      "discrepancy": false,
      "discrepancy_detail": null,
      "source": "tws"
    },
    {
      "expiry": "20260724",
      "strike": 592.5,
      "right": "P",
      "bid": null,
      "ask": null,
      "mid": 18.715,
      "last": null,
      "iv": 0.741,
      "iv_model": null,
      "iv_bs": null,
      "iv_reliable": true,
      "delta": -0.607,
      "gamma": 0.012,
      "vega": 0.17,
      "theta": -2.957,
      "open_interest": null,
      "volume": null,
      "discrepancy": false,
      "discrepancy_detail": null,
      "source": "bs-interp"
    },
    {
      "expiry": "20260724",
      "strike": 595.0,
      "right": "C",
      "bid": null,
      "ask": null,
      "mid": 7.877,
      "last": null,
      "iv": 0.738,
      "iv_model": null,
      "iv_bs": null,
      "iv_reliable": true,
      "delta": 0.364,
      "gamma": 0.012,
      "vega": 0.166,
      "theta": -2.934,
      "open_interest": null,
      "volume": null,
      "discrepancy": false,
      "discrepancy_detail": null,
      "source": "bs-interp"
    },
    {
      "expiry": "20260724",
      "strike": 595.0,
      "right": "P",
      "bid": null,
      "ask": null,
      "mid": 20.266,
      "last": null,
      "iv": 0.738,
      "iv_model": null,
      "iv_bs": null,
      "iv_reliable": true,
      "delta": -0.636,
      "gamma": 0.012,
      "vega": 0.166,
      "theta": -2.872,
      "open_interest": null,
      "volume": null,
      "discrepancy": false,
      "discrepancy_detail": null,
      "source": "bs-interp"
    },
    {
      "expiry": "20260724",
      "strike": 597.5,
      "right": "C",
      "bid": 6.55,
      "ask": 7.45,
      "mid": 7.0,
      "last": 7.53,
      "iv": 0.735,
      "iv_model": null,
      "iv_bs": 0.735,
      "iv_reliable": true,
      "delta": 0.336,
      "delta_bs": 0.336,
      "gamma": 0.011,
      "vega": 0.161,
      "theta": -2.835,
      "open_interest": 137.0,
      "volume": 18.0,
      "discrepancy": false,
      "discrepancy_detail": null,
      "source": "tws"
    },
    {
      "expiry": "20260724",
      "strike": 597.5,
      "right": "P",
      "bid": null,
      "ask": null,
      "mid": 21.889,
      "last": null,
      "iv": 0.735,
      "iv_model": null,
      "iv_bs": null,
      "iv_reliable": true,
      "delta": -0.664,
      "gamma": 0.011,
      "vega": 0.161,
      "theta": -2.772,
      "open_interest": null,
      "volume": null,
      "discrepancy": false,
      "discrepancy_detail": null,
      "source": "bs-interp"
    },
    {
      "expiry": "20260724",
      "strike": 600.0,
      "right": "C",
      "bid": null,
      "ask": null,
      "mid": 6.204,
      "last": null,
      "iv": 0.732,
      "iv_model": null,
      "iv_bs": null,
      "iv_reliable": true,
      "delta": 0.308,
      "gamma": 0.011,
      "vega": 0.155,
      "theta": -2.725,
      "open_interest": null,
      "volume": null,
      "discrepancy": false,
      "discrepancy_detail": null,
      "source": "bs-interp"
    },
    {
      "expiry": "20260724",
      "strike": 600.0,
      "right": "P",
      "bid": null,
      "ask": null,
      "mid": 23.592,
      "last": null,
      "iv": 0.732,
      "iv_model": null,
      "iv_bs": null,
      "iv_reliable": true,
      "delta": -0.692,
      "gamma": 0.011,
      "vega": 0.155,
      "theta": -2.662,
      "open_interest": null,
      "volume": null,
      "discrepancy": false,
      "discrepancy_detail": null,
      "source": "bs-interp"
    },
    {
      "expiry": "20260724",
      "strike": 602.5,
      "right": "C",
      "bid": 5.15,
      "ask": 5.8,
      "mid": 5.475,
      "last": 6.0,
      "iv": 0.729,
      "iv_model": null,
      "iv_bs": 0.73,
      "iv_reliable": true,
      "delta": 0.281,
      "delta_bs": 0.281,
      "gamma": 0.01,
      "vega": 0.149,
      "theta": -2.604,
      "open_interest": 228.0,
      "volume": 444.0,
      "discrepancy": false,
      "discrepancy_detail": null,
      "source": "tws"
    },
    {
      "expiry": "20260724",
      "strike": 602.5,
      "right": "P",
      "bid": null,
      "ask": null,
      "mid": 25.363,
      "last": null,
      "iv": 0.73,
      "iv_model": null,
      "iv_bs": null,
      "iv_reliable": true,
      "delta": -0.719,
      "gamma": 0.01,
      "vega": 0.149,
      "theta": -2.541,
      "open_interest": null,
      "volume": null,
      "discrepancy": false,
      "discrepancy_detail": null,
      "source": "bs-interp"
    }
  ],
  "flags": {
    "published_window": "ATM±8 strike (per rango, simmetrica)"
  },
  "ohlcv": [
    {
      "date": "2026-07-07",
      "o": 580.02,
      "h": 585.97,
      "l": 566.83,
      "c": 581.45,
      "v": 14619200.0,
      "source": "lake"
    },
    {
      "date": "2026-07-08",
      "o": 575.33,
      "h": 595.0,
      "l": 575.04,
      "c": 593.0,
      "v": 9521300.0,
      "source": "lake"
    },
    {
      "date": "2026-07-09",
      "o": 615.48,
      "h": 618.17,
      "l": 604.7,
      "c": 607.73,
      "v": 9045100.0,
      "source": "lake"
    },
    {
      "date": "2026-07-10",
      "o": 600.87,
      "h": 615.05,
      "l": 595.84,
      "c": 611.03,
      "v": 6608400.0,
      "source": "lake"
    },
    {
      "date": "2026-07-13",
      "o": 598.01,
      "h": 599.36,
      "l": 583.09,
      "c": 585.62,
      "v": 8709100.0,
      "source": "lake"
    },
    {
      "date": "2026-07-14",
      "o": 608.895,
      "h": 608.895,
      "l": 590.38,
      "c": 603.25,
      "v": 4554031.0,
      "source": "lake"
    },
    {
      "date": "2026-07-15",
      "o": 610.0,
      "h": 614.71,
      "l": 573.72,
      "c": 590.4,
      "v": 209925.0,
      "source": "lake"
    },
    {
      "date": "2026-07-16",
      "o": 583.32,
      "h": 592.8,
      "l": 564.45,
      "c": 568.2,
      "v": 218579.0,
      "source": "lake"
    },
    {
      "date": "2026-07-17",
      "o": 553.0,
      "h": 567.41,
      "l": 536.81,
      "c": 555.55,
      "v": 356533.0,
      "source": "lake"
    },
    {
      "date": "2026-07-20",
      "o": 556.66,
      "h": 572.77,
      "l": 556.66,
      "c": 557.25,
      "v": 134705.0,
      "source": "lake"
    },
    {
      "date": "2026-07-21",
      "o": 581.49,
      "h": 585.66,
      "l": 572.05,
      "c": 582.48,
      "v": 143637.0,
      "source": "tws",
      "partial": true
    }
  ],
  "integrity": {
    "checksum_algo": "sha256",
    "checksum_fields": [
      "symbol",
      "conId",
      "exchange",
      "currency",
      "timestamp_fetch",
      "data_type",
      "spot",
      "open",
      "high",
      "low",
      "prior_close",
      "volume",
      "iv_underlying",
      "hv",
      "vwap",
      "poc",
      "week52_high",
      "week52_low",
      "avg_volume_20d",
      "options[]:expiry",
      "options[]:strike",
      "options[]:right",
      "options[]:bid",
      "options[]:ask",
      "options[]:iv",
      "options[]:delta",
      "options[]:open_interest"
    ],
    "checksum": "acbe80459498898227dabfa38c93ba78c8057f3c3a75e63a49945a5ac90ceb46",
    "generated_at": "2026-07-21T21:31:20+02:00",
    "generator": "TCC scheda_ticker v0.3",
    "last_commit": {
      "author": null,
      "timestamp": null
    }
  }
}