{
  "schema_version": "1.2",
  "ticker": "STAG",
  "stamp": {
    "timestamp_fetch": "2026-07-24T18:46:50+02:00",
    "data_type": "delayed",
    "lag_stimato_min": 20,
    "usage_layer": "context",
    "lake_status": "ready"
  },
  "underlying": {
    "symbol": "STAG",
    "conId": 86792819,
    "exchange": "NYSE",
    "currency": "USD",
    "spot": 41.23,
    "open": 40.82,
    "high": 41.33,
    "low": 40.75,
    "prior_close": 40.5,
    "volume": 10863.0,
    "change_pct": 1.8,
    "iv_underlying": 0.197,
    "hv": 0.194,
    "iv_rank_52w": 21.0,
    "iv_percentile_52w": 26.7,
    "week52_high": 42.6,
    "week52_low": 33.72,
    "avg_volume_20d": 1207288,
    "vwap": 41.103,
    "vwap_source": "yahoo",
    "vwap_method": "VWAP typical-price barre 1m STAG sessione corrente",
    "poc": 41.158,
    "poc_source": "yahoo",
    "poc_method": "volume-profile 50 bin, barre 5m STAG sessione corrente",
    "oi_totals": {
      "call": 2224.0,
      "put": 805.0,
      "put_call": 0.362
    }
  },
  "data_availability": {
    "hv": "ok",
    "iv_rank_52w": "ok",
    "iv_percentile_52w": "ok",
    "avg_volume_20d": "ok",
    "week52_high": "ok",
    "week52_low": "ok",
    "vwap": "ok",
    "poc": "ok",
    "ohlcv": "ok"
  },
  "option_params": {
    "exchange": "BOX",
    "trading_class": "STAG",
    "multiplier": "100",
    "currency": "USD",
    "source": "reqSecDefOptParams"
  },
  "expirations": [
    "20260821",
    "20260918"
  ],
  "bs_assumptions": {
    "r": 0.04,
    "q": 0.038,
    "q_source": "dividendo_annuo/spot (tick 456)",
    "daycount": "ACT/365",
    "price_used": "mid"
  },
  "options": [
    {
      "expiry": "20260821",
      "strike": 20.0,
      "right": "C",
      "bid": null,
      "ask": null,
      "mid": 21.174,
      "last": null,
      "iv": 0.64,
      "iv_model": null,
      "iv_bs": null,
      "iv_reliable": true,
      "delta": 0.997,
      "gamma": 0.0,
      "vega": 0.0,
      "theta": 0.002,
      "open_interest": null,
      "volume": null,
      "discrepancy": false,
      "discrepancy_detail": null,
      "source": "bs-interp"
    },
    {
      "expiry": "20260821",
      "strike": 20.0,
      "right": "P",
      "bid": null,
      "ask": 0.75,
      "mid": null,
      "last": null,
      "iv": 0.64,
      "iv_model": 0.64,
      "iv_bs": null,
      "iv_reliable": true,
      "delta": -0.0,
      "delta_bs": -0.0,
      "gamma": 0.0,
      "vega": 0.0,
      "theta": -0.0,
      "open_interest": 0.0,
      "volume": 0.0,
      "discrepancy": false,
      "discrepancy_detail": null,
      "source": "tws"
    },
    {
      "expiry": "20260821",
      "strike": 22.5,
      "right": "C",
      "bid": null,
      "ask": null,
      "mid": 18.682,
      "last": null,
      "iv": 0.595,
      "iv_model": null,
      "iv_bs": null,
      "iv_reliable": true,
      "delta": 0.997,
      "gamma": 0.0,
      "vega": 0.0,
      "theta": 0.002,
      "open_interest": null,
      "volume": null,
      "discrepancy": false,
      "discrepancy_detail": null,
      "source": "bs-interp"
    },
    {
      "expiry": "20260821",
      "strike": 22.5,
      "right": "P",
      "bid": null,
      "ask": null,
      "mid": 0.0,
      "last": null,
      "iv": 0.595,
      "iv_model": null,
      "iv_bs": null,
      "iv_reliable": true,
      "delta": -0.0,
      "gamma": 0.0,
      "vega": 0.0,
      "theta": -0.0,
      "open_interest": null,
      "volume": null,
      "discrepancy": false,
      "discrepancy_detail": null,
      "source": "bs-interp"
    },
    {
      "expiry": "20260821",
      "strike": 25.0,
      "right": "C",
      "bid": null,
      "ask": null,
      "mid": 16.19,
      "last": null,
      "iv": 0.549,
      "iv_model": null,
      "iv_bs": null,
      "iv_reliable": true,
      "delta": 0.997,
      "gamma": 0.0,
      "vega": 0.0,
      "theta": 0.001,
      "open_interest": null,
      "volume": null,
      "discrepancy": false,
      "discrepancy_detail": null,
      "source": "bs-interp"
    },
    {
      "expiry": "20260821",
      "strike": 25.0,
      "right": "P",
      "bid": null,
      "ask": 0.3,
      "mid": null,
      "last": null,
      "iv": 0.549,
      "iv_model": 0.549,
      "iv_bs": null,
      "iv_reliable": true,
      "delta": -0.0,
      "delta_bs": -0.0,
      "gamma": 0.0,
      "vega": 0.0,
      "theta": -0.0,
      "open_interest": 0.0,
      "volume": 0.0,
      "discrepancy": false,
      "discrepancy_detail": null,
      "source": "tws"
    },
    {
      "expiry": "20260821",
      "strike": 30.0,
      "right": "C",
      "bid": null,
      "ask": null,
      "mid": 11.207,
      "last": null,
      "iv": 0.417,
      "iv_model": null,
      "iv_bs": null,
      "iv_reliable": true,
      "delta": 0.995,
      "gamma": 0.001,
      "vega": 0.001,
      "theta": 0.0,
      "open_interest": null,
      "volume": null,
      "discrepancy": false,
      "discrepancy_detail": null,
      "source": "bs-interp"
    },
    {
      "expiry": "20260821",
      "strike": 30.0,
      "right": "P",
      "bid": null,
      "ask": null,
      "mid": 0.003,
      "last": null,
      "iv": 0.417,
      "iv_model": null,
      "iv_bs": null,
      "iv_reliable": true,
      "delta": -0.002,
      "gamma": 0.001,
      "vega": 0.001,
      "theta": -0.001,
      "open_interest": null,
      "volume": null,
      "discrepancy": false,
      "discrepancy_detail": null,
      "source": "bs-interp"
    },
    {
      "expiry": "20260821",
      "strike": 35.0,
      "right": "C",
      "bid": null,
      "ask": null,
      "mid": 6.238,
      "last": null,
      "iv": 0.286,
      "iv_model": null,
      "iv_bs": null,
      "iv_reliable": true,
      "delta": 0.981,
      "gamma": 0.012,
      "vega": 0.004,
      "theta": -0.002,
      "open_interest": null,
      "volume": null,
      "discrepancy": false,
      "discrepancy_detail": null,
      "source": "bs-interp"
    },
    {
      "expiry": "20260821",
      "strike": 35.0,
      "right": "P",
      "bid": null,
      "ask": 0.35,
      "mid": null,
      "last": null,
      "iv": 0.286,
      "iv_model": 0.286,
      "iv_bs": null,
      "iv_reliable": true,
      "delta": -0.016,
      "delta_bs": -0.016,
      "gamma": 0.012,
      "vega": 0.004,
      "theta": -0.002,
      "open_interest": 41.0,
      "volume": 0.0,
      "discrepancy": false,
      "discrepancy_detail": null,
      "source": "tws"
    },
    {
      "expiry": "20260821",
      "strike": 40.0,
      "right": "C",
      "bid": null,
      "ask": null,
      "mid": 1.823,
      "last": null,
      "iv": 0.249,
      "iv_model": null,
      "iv_bs": null,
      "iv_reliable": true,
      "delta": 0.683,
      "gamma": 0.126,
      "vega": 0.04,
      "theta": -0.018,
      "open_interest": null,
      "volume": null,
      "discrepancy": false,
      "discrepancy_detail": null,
      "source": "bs-interp"
    },
    {
      "expiry": "20260821",
      "strike": 40.0,
      "right": "P",
      "bid": 0.3,
      "ask": 1.0,
      "mid": 0.65,
      "last": null,
      "iv": 0.249,
      "iv_model": 0.249,
      "iv_bs": null,
      "iv_reliable": true,
      "delta": -0.314,
      "delta_bs": -0.314,
      "gamma": 0.126,
      "vega": 0.04,
      "theta": -0.018,
      "open_interest": null,
      "volume": 0.0,
      "discrepancy": false,
      "discrepancy_detail": null,
      "source": "tws"
    },
    {
      "expiry": "20260821",
      "strike": 45.0,
      "right": "C",
      "bid": null,
      "ask": 0.95,
      "mid": null,
      "last": null,
      "iv": null,
      "iv_model": null,
      "iv_bs": null,
      "iv_reliable": false,
      "delta": null,
      "delta_bs": null,
      "gamma": null,
      "vega": null,
      "theta": null,
      "open_interest": null,
      "volume": 0.0,
      "discrepancy": false,
      "discrepancy_detail": null,
      "source": "tws"
    },
    {
      "expiry": "20260821",
      "strike": 45.0,
      "right": "P",
      "bid": null,
      "ask": null,
      "mid": 3.889,
      "last": null,
      "iv": 0.249,
      "iv_model": null,
      "iv_bs": null,
      "iv_reliable": true,
      "delta": -0.892,
      "gamma": 0.065,
      "vega": 0.021,
      "theta": -0.009,
      "open_interest": null,
      "volume": null,
      "discrepancy": false,
      "discrepancy_detail": null,
      "source": "bs-interp"
    },
    {
      "expiry": "20260821",
      "strike": 50.0,
      "right": "C",
      "bid": null,
      "ask": null,
      "mid": 0.002,
      "last": null,
      "iv": 0.249,
      "iv_model": null,
      "iv_bs": null,
      "iv_reliable": true,
      "delta": 0.003,
      "gamma": 0.003,
      "vega": 0.001,
      "theta": -0.0,
      "open_interest": null,
      "volume": null,
      "discrepancy": false,
      "discrepancy_detail": null,
      "source": "bs-interp"
    },
    {
      "expiry": "20260821",
      "strike": 50.0,
      "right": "P",
      "bid": null,
      "ask": null,
      "mid": 8.739,
      "last": null,
      "iv": 0.249,
      "iv_model": null,
      "iv_bs": null,
      "iv_reliable": true,
      "delta": -0.995,
      "gamma": 0.003,
      "vega": 0.001,
      "theta": 0.001,
      "open_interest": null,
      "volume": null,
      "discrepancy": false,
      "discrepancy_detail": null,
      "source": "bs-interp"
    },
    {
      "expiry": "20260821",
      "strike": 55.0,
      "right": "C",
      "bid": null,
      "ask": 0.95,
      "mid": null,
      "last": null,
      "iv": null,
      "iv_model": null,
      "iv_bs": null,
      "iv_reliable": false,
      "delta": null,
      "delta_bs": null,
      "gamma": null,
      "vega": null,
      "theta": null,
      "open_interest": 0.0,
      "volume": 0.0,
      "discrepancy": false,
      "discrepancy_detail": null,
      "source": "tws"
    },
    {
      "expiry": "20260821",
      "strike": 55.0,
      "right": "P",
      "bid": null,
      "ask": null,
      "mid": 13.722,
      "last": null,
      "iv": 0.249,
      "iv_model": null,
      "iv_bs": null,
      "iv_reliable": true,
      "delta": -0.997,
      "gamma": 0.0,
      "vega": 0.0,
      "theta": 0.002,
      "open_interest": null,
      "volume": null,
      "discrepancy": false,
      "discrepancy_detail": null,
      "source": "bs-interp"
    },
    {
      "expiry": "20260918",
      "strike": 20.0,
      "right": "C",
      "bid": null,
      "ask": null,
      "mid": 21.117,
      "last": null,
      "iv": 0.212,
      "iv_model": null,
      "iv_bs": null,
      "iv_reliable": true,
      "delta": 0.994,
      "gamma": 0.0,
      "vega": 0.0,
      "theta": 0.002,
      "open_interest": null,
      "volume": null,
      "discrepancy": false,
      "discrepancy_detail": null,
      "source": "bs-interp"
    },
    {
      "expiry": "20260918",
      "strike": 20.0,
      "right": "P",
      "bid": null,
      "ask": 0.75,
      "mid": null,
      "last": null,
      "iv": null,
      "iv_model": null,
      "iv_bs": null,
      "iv_reliable": false,
      "delta": null,
      "delta_bs": null,
      "gamma": null,
      "vega": null,
      "theta": null,
      "open_interest": 0.0,
      "volume": 0.0,
      "discrepancy": false,
      "discrepancy_detail": null,
      "source": "tws"
    },
    {
      "expiry": "20260918",
      "strike": 22.5,
      "right": "C",
      "bid": null,
      "ask": null,
      "mid": 18.632,
      "last": null,
      "iv": 0.212,
      "iv_model": null,
      "iv_bs": null,
      "iv_reliable": true,
      "delta": 0.994,
      "gamma": 0.0,
      "vega": 0.0,
      "theta": 0.002,
      "open_interest": null,
      "volume": null,
      "discrepancy": false,
      "discrepancy_detail": null,
      "source": "bs-interp"
    },
    {
      "expiry": "20260918",
      "strike": 22.5,
      "right": "P",
      "bid": null,
      "ask": null,
      "mid": 0.0,
      "last": null,
      "iv": 0.212,
      "iv_model": null,
      "iv_bs": null,
      "iv_reliable": true,
      "delta": -0.0,
      "gamma": 0.0,
      "vega": 0.0,
      "theta": -0.0,
      "open_interest": null,
      "volume": null,
      "discrepancy": false,
      "discrepancy_detail": null,
      "source": "bs-interp"
    },
    {
      "expiry": "20260918",
      "strike": 25.0,
      "right": "C",
      "bid": null,
      "ask": null,
      "mid": 16.147,
      "last": null,
      "iv": 0.212,
      "iv_model": null,
      "iv_bs": null,
      "iv_reliable": true,
      "delta": 0.994,
      "gamma": 0.0,
      "vega": 0.0,
      "theta": 0.002,
      "open_interest": null,
      "volume": null,
      "discrepancy": false,
      "discrepancy_detail": null,
      "source": "bs-interp"
    },
    {
      "expiry": "20260918",
      "strike": 25.0,
      "right": "P",
      "bid": null,
      "ask": 0.75,
      "mid": null,
      "last": null,
      "iv": null,
      "iv_model": null,
      "iv_bs": null,
      "iv_reliable": false,
      "delta": null,
      "delta_bs": null,
      "gamma": null,
      "vega": null,
      "theta": null,
      "open_interest": 0.0,
      "volume": 0.0,
      "discrepancy": false,
      "discrepancy_detail": null,
      "source": "tws"
    },
    {
      "expiry": "20260918",
      "strike": 30.0,
      "right": "C",
      "bid": null,
      "ask": null,
      "mid": 11.177,
      "last": null,
      "iv": 0.212,
      "iv_model": null,
      "iv_bs": null,
      "iv_reliable": true,
      "delta": 0.994,
      "gamma": 0.0,
      "vega": 0.0,
      "theta": 0.001,
      "open_interest": null,
      "volume": null,
      "discrepancy": false,
      "discrepancy_detail": null,
      "source": "bs-interp"
    },
    {
      "expiry": "20260918",
      "strike": 30.0,
      "right": "P",
      "bid": null,
      "ask": null,
      "mid": 0.0,
      "last": null,
      "iv": 0.212,
      "iv_model": null,
      "iv_bs": null,
      "iv_reliable": true,
      "delta": -0.0,
      "gamma": 0.0,
      "vega": 0.0,
      "theta": -0.0,
      "open_interest": null,
      "volume": null,
      "discrepancy": false,
      "discrepancy_detail": null,
      "source": "bs-interp"
    },
    {
      "expiry": "20260918",
      "strike": 35.0,
      "right": "C",
      "bid": null,
      "ask": null,
      "mid": 6.234,
      "last": null,
      "iv": 0.212,
      "iv_model": null,
      "iv_bs": null,
      "iv_reliable": true,
      "delta": 0.973,
      "gamma": 0.015,
      "vega": 0.008,
      "theta": -0.001,
      "open_interest": null,
      "volume": null,
      "discrepancy": false,
      "discrepancy_detail": null,
      "source": "bs-interp"
    },
    {
      "expiry": "20260918",
      "strike": 35.0,
      "right": "P",
      "bid": 0.15,
      "ask": 0.5,
      "mid": 0.325,
      "last": null,
      "iv": null,
      "iv_model": null,
      "iv_bs": null,
      "iv_reliable": false,
      "delta": -0.109,
      "delta_bs": -0.109,
      "gamma": 0.032,
      "vega": 0.03,
      "theta": -0.01,
      "open_interest": 127.0,
      "volume": 0.0,
      "discrepancy": false,
      "discrepancy_detail": null,
      "source": "tws"
    },
    {
      "expiry": "20260918",
      "strike": 40.0,
      "right": "C",
      "bid": null,
      "ask": null,
      "mid": 2.038,
      "last": null,
      "iv": 0.212,
      "iv_model": null,
      "iv_bs": null,
      "iv_reliable": true,
      "delta": 0.656,
      "gamma": 0.107,
      "vega": 0.058,
      "theta": -0.011,
      "open_interest": null,
      "volume": null,
      "discrepancy": false,
      "discrepancy_detail": null,
      "source": "bs-interp"
    },
    {
      "expiry": "20260918",
      "strike": 40.0,
      "right": "P",
      "bid": 0.5,
      "ask": 1.1,
      "mid": 0.8,
      "last": null,
      "iv": 0.212,
      "iv_model": null,
      "iv_bs": 0.212,
      "iv_reliable": true,
      "delta": -0.338,
      "delta_bs": -0.338,
      "gamma": 0.107,
      "vega": 0.058,
      "theta": -0.011,
      "open_interest": 11.0,
      "volume": 0.0,
      "discrepancy": false,
      "discrepancy_detail": null,
      "source": "tws"
    },
    {
      "expiry": "20260918",
      "strike": 45.0,
      "right": "C",
      "bid": 0.1,
      "ask": 0.25,
      "mid": 0.175,
      "last": 0.18,
      "iv": 0.187,
      "iv_model": null,
      "iv_bs": 0.187,
      "iv_reliable": true,
      "delta": 0.122,
      "delta_bs": 0.122,
      "gamma": 0.067,
      "vega": 0.032,
      "theta": -0.005,
      "open_interest": 143.0,
      "volume": 1.0,
      "discrepancy": false,
      "discrepancy_detail": null,
      "source": "tws"
    },
    {
      "expiry": "20260918",
      "strike": 45.0,
      "right": "P",
      "bid": null,
      "ask": null,
      "mid": 3.907,
      "last": null,
      "iv": 0.187,
      "iv_model": null,
      "iv_bs": null,
      "iv_reliable": true,
      "delta": -0.873,
      "gamma": 0.067,
      "vega": 0.032,
      "theta": -0.005,
      "open_interest": null,
      "volume": null,
      "discrepancy": false,
      "discrepancy_detail": null,
      "source": "bs-interp"
    },
    {
      "expiry": "20260918",
      "strike": 50.0,
      "right": "C",
      "bid": null,
      "ask": null,
      "mid": 0.004,
      "last": null,
      "iv": 0.187,
      "iv_model": null,
      "iv_bs": null,
      "iv_reliable": true,
      "delta": 0.004,
      "gamma": 0.004,
      "vega": 0.002,
      "theta": -0.0,
      "open_interest": null,
      "volume": null,
      "discrepancy": false,
      "discrepancy_detail": null,
      "source": "bs-interp"
    },
    {
      "expiry": "20260918",
      "strike": 50.0,
      "right": "P",
      "bid": null,
      "ask": null,
      "mid": 8.706,
      "last": null,
      "iv": 0.187,
      "iv_model": null,
      "iv_bs": null,
      "iv_reliable": true,
      "delta": -0.99,
      "gamma": 0.004,
      "vega": 0.002,
      "theta": 0.001,
      "open_interest": null,
      "volume": null,
      "discrepancy": false,
      "discrepancy_detail": null,
      "source": "bs-interp"
    },
    {
      "expiry": "20260918",
      "strike": 55.0,
      "right": "C",
      "bid": null,
      "ask": 0.2,
      "mid": null,
      "last": null,
      "iv": null,
      "iv_model": null,
      "iv_bs": null,
      "iv_reliable": false,
      "delta": null,
      "delta_bs": null,
      "gamma": null,
      "vega": null,
      "theta": null,
      "open_interest": 1.0,
      "volume": 0.0,
      "discrepancy": false,
      "discrepancy_detail": null,
      "source": "tws"
    },
    {
      "expiry": "20260918",
      "strike": 55.0,
      "right": "P",
      "bid": null,
      "ask": null,
      "mid": 13.672,
      "last": null,
      "iv": 0.187,
      "iv_model": null,
      "iv_bs": null,
      "iv_reliable": true,
      "delta": -0.994,
      "gamma": 0.0,
      "vega": 0.0,
      "theta": 0.002,
      "open_interest": null,
      "volume": null,
      "discrepancy": false,
      "discrepancy_detail": null,
      "source": "bs-interp"
    }
  ],
  "flags": {
    "published_window": "ATM±8 strike (per rango, simmetrica)"
  },
  "ohlcv": [
    {
      "date": "2026-07-08",
      "o": 39.16,
      "h": 39.31,
      "l": 38.52,
      "c": 38.6,
      "v": 1576700.0,
      "source": "lake"
    },
    {
      "date": "2026-07-09",
      "o": 38.79,
      "h": 39.16,
      "l": 38.65,
      "c": 38.92,
      "v": 975400.0,
      "source": "lake"
    },
    {
      "date": "2026-07-10",
      "o": 39.16,
      "h": 39.16,
      "l": 38.66,
      "c": 38.98,
      "v": 1091800.0,
      "source": "lake"
    },
    {
      "date": "2026-07-13",
      "o": 39.0,
      "h": 39.36,
      "l": 39.0,
      "c": 39.08,
      "v": 2541200.0,
      "source": "lake"
    },
    {
      "date": "2026-07-14",
      "o": 39.22,
      "h": 39.28,
      "l": 38.91,
      "c": 39.065,
      "v": 1142961.0,
      "source": "lake"
    },
    {
      "date": "2026-07-15",
      "o": 39.61,
      "h": 40.22,
      "l": 39.61,
      "c": 39.92,
      "v": 5868.0,
      "source": "lake"
    },
    {
      "date": "2026-07-16",
      "o": 40.16,
      "h": 42.09,
      "l": 40.16,
      "c": 42.04,
      "v": 4671.0,
      "source": "lake"
    },
    {
      "date": "2026-07-17",
      "o": 42.11,
      "h": 42.6,
      "l": 41.48,
      "c": 41.68,
      "v": 4069.0,
      "source": "lake"
    },
    {
      "date": "2026-07-20",
      "o": 41.68,
      "h": 42.17,
      "l": 41.63,
      "c": 41.82,
      "v": 3455.0,
      "source": "lake"
    },
    {
      "date": "2026-07-21",
      "o": 41.93,
      "h": 42.06,
      "l": 41.6,
      "c": 41.77,
      "v": 4737.0,
      "source": "lake"
    },
    {
      "date": "2026-07-24",
      "o": 40.82,
      "h": 41.33,
      "l": 40.75,
      "c": 41.23,
      "v": 10863.0,
      "source": "tws",
      "partial": true
    }
  ],
  "integrity": {
    "checksum_algo": "sha256",
    "checksum_fields": [
      "symbol",
      "conId",
      "exchange",
      "currency",
      "timestamp_fetch",
      "data_type",
      "spot",
      "open",
      "high",
      "low",
      "prior_close",
      "volume",
      "iv_underlying",
      "hv",
      "vwap",
      "poc",
      "week52_high",
      "week52_low",
      "avg_volume_20d",
      "options[]:expiry",
      "options[]:strike",
      "options[]:right",
      "options[]:bid",
      "options[]:ask",
      "options[]:iv",
      "options[]:delta",
      "options[]:open_interest"
    ],
    "checksum": "75014001a69d64f43dab9e3777341ba8f2ed01e64169e6c25cf2dc0c316ad053",
    "generated_at": "2026-07-24T18:46:50+02:00",
    "generator": "TCC scheda_ticker v0.3",
    "last_commit": {
      "author": null,
      "timestamp": null
    }
  }
}